envconfig/__init__.py
envconfig/dotenv.py
envconfig/parser.py
envconfig/py.typed
envconfig/setting_types.py
envconfig/settings.py
envconfig/utils.py
django_envconfig-0.4.0.dist-info/LICENSE
django_envconfig-0.4.0.dist-info/METADATA
django_envconfig-0.4.0.dist-info/WHEEL
django_envconfig-0.4.0.dist-info/top_level.txt
django_envconfig-0.4.0.dist-info/RECORD
